src/marcuslion-pylib/main.py
marcuslion_pylib-0.1.0.dist-info/METADATA
marcuslion_pylib-0.1.0.dist-info/WHEEL
marcuslion_pylib-0.1.0.dist-info/licenses/LICENSE
marcuslion_pylib-0.1.0.dist-info/RECORD
