Metadata-Version: 2.1
Name: marcuslion-pylib
Version: 0.1.0
Summary: Marcus Lion Platform library package
Project-URL: Homepage, https://github.com/Marcus-Lion/ml-samples.git
Project-URL: Bug Tracker, https://github.com/Marcus-Lion/ml-samples.git/issues
Author-email: Marc <support@marcuslion.com>
License-File: LICENSE
Classifier: License :: OSI Approved :: MIT License
Classifier: Operating System :: OS Independent
Classifier: Programming Language :: Python :: 3
Requires-Python: >=3.7
